{
    "L08_課文文件": {
        "paragraphs": {
            "1": {
                "english_with_html": "<div class=\"paragraph\" data-paragraph=\"1\"><span data-end=\"14.82\" data-start=\"14.10\">It</span> <span data-end=\"15.54\" data-start=\"14.82\">has</span> <span data-end=\"16.04\" data-start=\"15.54\">probably</span> <span data-end=\"16.52\" data-start=\"16.04\">happened</span> <span data-end=\"17.02\" data-start=\"16.52\">to</span> <span data-end=\"17.26\" data-start=\"17.02\">you</span> <span data-end=\"17.72\" data-start=\"17.26\">before</span>. <span data-end=\"18.56\" data-start=\"18.42\">The</span> <span data-end=\"18.88\" data-start=\"18.56\">glass</span> <span data-end=\"19.24\" data-start=\"18.88\">doors</span> <span data-end=\"19.48\" data-start=\"19.24\">of</span> <span data-end=\"19.62\" data-start=\"19.48\">the</span> <span data-end=\"20.06\" data-start=\"19.62\">convenience</span> <span data-end=\"20.58\" data-start=\"20.06\">store</span> <span data-end=\"21.22\" data-start=\"20.58\">slide</span> <span data-end=\"21.80\" data-start=\"21.22\">open</span> <b id=\"wr_1\"><span data-end=\"22.74\" data-start=\"21.80\">invitingly</span></b>*; <span data-end=\"23.62\" data-start=\"23.48\">you</span> <span data-end=\"23.88\" data-start=\"23.62\">hear</span> <span data-end=\"24.10\" data-start=\"23.88\">the</span> <b id=\"wp_1\"><span data-end=\"24.46\" data-start=\"24.10\">familiar</span></b><span style=\"color: #0070C0\"><sup><span data-end=\"24.96\" data-start=\"24.71\">1</span></sup>\n</span> “<span data-end=\"25.22\" data-start=\"24.96\">Welcome</span>!” <span data-end=\"26.18\" data-start=\"25.92\">and</span> <span data-end=\"26.56\" data-start=\"26.18\">enter</span> <span data-end=\"26.92\" data-start=\"26.56\">just</span> <span data-end=\"27.12\" data-start=\"26.92\">to</span> <span data-end=\"27.30\" data-start=\"27.12\">pick</span> <span data-end=\"27.48\" data-start=\"27.30\">up</span> <span data-end=\"27.76\" data-start=\"27.48\">one</span> <span data-end=\"28.10\" data-start=\"27.76\">item</span>. <span data-end=\"29.08\" data-start=\"28.76\">A</span> <span data-end=\"29.28\" data-start=\"29.08\">few</span> <span data-end=\"29.60\" data-start=\"29.28\">minutes</span> <span data-end=\"29.94\" data-start=\"29.60\">later</span>, <span data-end=\"30.38\" data-start=\"30.24\">you</span> <span data-end=\"30.68\" data-start=\"30.38\">walk</span> <span data-end=\"30.92\" data-start=\"30.68\">out</span> <span data-end=\"31.12\" data-start=\"30.92\">with</span> <span data-end=\"31.26\" data-start=\"31.12\">a</span> <span data-end=\"31.46\" data-start=\"31.26\">whole</span> <span data-end=\"31.84\" data-start=\"31.46\">bag</span> <span data-end=\"32.08\" data-start=\"31.84\">full</span> <span data-end=\"32.24\" data-start=\"32.08\">of</span> <span data-end=\"32.62\" data-start=\"32.24\">drinks</span>, <span data-end=\"33.30\" data-start=\"32.88\">snacks</span>, <span data-end=\"33.64\" data-start=\"33.54\">and</span> <span data-end=\"33.94\" data-start=\"33.64\">other</span> <b id=\"wr_2\"><span data-end=\"34.40\" data-start=\"33.94\">goodies</span></b>* <span data-end=\"34.98\" data-start=\"34.40\">you</span> <span data-end=\"35.28\" data-start=\"34.98\">never</span> <span data-end=\"35.70\" data-start=\"35.28\">even</span> <span data-end=\"36.02\" data-start=\"35.70\">thought</span> <span data-end=\"36.18\" data-start=\"36.02\">of</span> <span data-end=\"36.56\" data-start=\"36.18\">buying</span>! </div>"
            },
            "2": {
                "english_with_html": "<div class=\"paragraph\" data-paragraph=\"2\"><span data-end=\"37.98\" data-start=\"37.34\">There’s</span> <span data-end=\"38.22\" data-start=\"37.98\">no</span> <span data-end=\"38.46\" data-start=\"38.22\">need</span> <span data-end=\"38.62\" data-start=\"38.46\">to</span> <span data-end=\"38.84\" data-start=\"38.62\">be</span> <span data-end=\"39.46\" data-start=\"38.84\">embarrassed</span> <span data-end=\"40.10\" data-start=\"39.46\">if</span> <span data-end=\"40.32\" data-start=\"40.10\">you’ve</span> <span data-end=\"40.98\" data-start=\"40.32\">experienced</span> <span data-end=\"41.30\" data-start=\"40.98\">this</span> <span data-end=\"41.68\" data-start=\"41.30\">sudden</span> <b id=\"wp_2\"><span data-end=\"42.10\" data-start=\"41.68\">urge</span></b><span style=\"color: #0070C0\"><sup><span data-end=\"42.10\" data-start=\"42.10\">2</span></sup></span> <span data-end=\"42.34\" data-start=\"42.10\">to</span> <span data-end=\"42.80\" data-start=\"42.34\">shop</span>. <span data-end=\"44.30\" data-start=\"43.66\">Convenience</span> <span data-end=\"44.60\" data-start=\"44.30\">stores</span> <span data-end=\"44.98\" data-start=\"44.60\">use</span> <span data-end=\"45.32\" data-start=\"44.98\">certain</span> <b id=\"wp_3\"><span data-end=\"45.96\" data-start=\"45.32\">strategies</span></b><span style=\"color: #0070C0\"><sup><span data-end=\"45.96\" data-start=\"45.96\">3</span></sup></span> <span data-end=\"46.66\" data-start=\"45.96\">to</span> <span data-end=\"46.90\" data-start=\"46.66\">make</span> <span data-end=\"47.04\" data-start=\"46.90\">you</span> <span data-end=\"47.36\" data-start=\"47.04\">feel</span> <span data-end=\"47.60\" data-start=\"47.36\">this</span> <span data-end=\"47.94\" data-start=\"47.60\">way</span>. <span data-end=\"48.96\" data-start=\"48.72\">One</span> <span data-end=\"49.10\" data-start=\"48.96\">of</span> <span data-end=\"49.26\" data-start=\"49.10\">these</span> <span data-end=\"49.78\" data-start=\"49.26\">strategies</span> <span data-end=\"50.42\" data-start=\"49.78\">is</span> <span data-end=\"50.60\" data-start=\"50.42\">to</span> <span data-end=\"50.88\" data-start=\"50.60\">follow</span> <span data-end=\"51.10\" data-start=\"50.88\">the</span> “<b id=\"wr_3\"><span data-end=\"51.56\" data-start=\"51.10\">eye</span> <span data-end=\"51.98\" data-start=\"51.56\">level</span></b>* <span data-end=\"52.70\" data-start=\"51.98\">is</span> <span data-end=\"53.22\" data-start=\"52.70\">buy</span> <span data-end=\"53.56\" data-start=\"53.22\">level</span>” <span data-end=\"54.06\" data-start=\"53.56\">rule</span>. <span data-end=\"55.14\" data-start=\"54.78\">The</span> <span data-end=\"55.36\" data-start=\"55.14\">more</span> <b id=\"wp_4\"><span data-end=\"55.82\" data-start=\"55.36\">visible</span></b><span style=\"color: #0070C0\"><sup><span data-end=\"55.82\" data-start=\"55.82\">4</span></sup></span> <span data-end=\"56.08\" data-start=\"55.82\">the</span> <span data-end=\"56.46\" data-start=\"56.08\">products</span> <span data-end=\"56.84\" data-start=\"56.46\">are</span>, <span data-end=\"57.44\" data-start=\"57.28\">the</span> <span data-end=\"57.94\" data-start=\"57.44\">easier</span> <span data-end=\"58.12\" data-start=\"57.94\">it</span> <span data-end=\"58.30\" data-start=\"58.12\">is</span> <span data-end=\"58.48\" data-start=\"58.30\">for</span> <span data-end=\"58.98\" data-start=\"58.48\">shoppers</span> <span data-end=\"59.22\" data-start=\"58.98\">to</span> <span data-end=\"59.52\" data-start=\"59.22\">notice</span> <span data-end=\"60.02\" data-start=\"59.52\">and</span> <b id=\"wp_5\"><span data-end=\"60.44\" data-start=\"60.02\">purchase</span></b><span style=\"color: #0070C0\"><sup><span data-end=\"60.44\" data-start=\"60.44\">5</span></sup></span> <span data-end=\"60.82\" data-start=\"60.44\">them</span>. <span data-end=\"62.32\" data-start=\"61.60\">Therefore</span>, <span data-end=\"63.16\" data-start=\"62.86\">smart</span> <span data-end=\"63.56\" data-start=\"63.16\">shop</span> <span data-end=\"63.88\" data-start=\"63.56\">owners</span> <span data-end=\"64.34\" data-start=\"63.88\">usually</span> <span data-end=\"64.80\" data-start=\"64.34\">place</span> <span data-end=\"64.98\" data-start=\"64.80\">their</span> <span data-end=\"65.22\" data-start=\"64.98\">most</span> <b id=\"wp_6\"><span data-end=\"65.82\" data-start=\"65.22\">profitable</span></b><span style=\"color: #0070C0\"><sup><span data-end=\"65.82\" data-start=\"65.82\">6</span></sup></span> <span data-end=\"66.62\" data-start=\"65.82\">and</span> <span data-end=\"67.20\" data-start=\"66.62\">popular</span> <span data-end=\"67.72\" data-start=\"67.20\">items</span> <span data-end=\"68.16\" data-start=\"67.72\">at</span> <span data-end=\"68.32\" data-start=\"68.16\">the</span> <span data-end=\"68.72\" data-start=\"68.32\">average</span> <span data-end=\"69.26\" data-start=\"68.72\">shopper’s</span> <span data-end=\"69.48\" data-start=\"69.26\">eye</span> <span data-end=\"69.84\" data-start=\"69.48\">level</span> <span data-end=\"70.50\" data-start=\"69.84\">to</span> <span data-end=\"70.74\" data-start=\"70.50\">make</span> <span data-end=\"71.00\" data-start=\"70.74\">sure</span> <span data-end=\"71.22\" data-start=\"71.00\">that</span> <span data-end=\"71.56\" data-start=\"71.22\">those</span> <span data-end=\"71.94\" data-start=\"71.56\">items</span> <span style=\"color: #0070C0\"><b id=\"ip_1\"><span data-end=\"72.20\" data-start=\"71.94\">are</span></b></span> <span data-end=\"72.46\" data-start=\"72.20\">most</span> <span style=\"color: #0070C0\"><b id=\"ip_1\"><span data-end=\"72.92\" data-start=\"72.46\">likely</span> <span data-end=\"73.20\" data-start=\"72.92\">to</span></b></span> <span data-end=\"73.34\" data-start=\"73.20\">be</span> <span data-end=\"73.84\" data-start=\"73.34\">seen</span>. <b id=\"wp_7\"><span data-end=\"75.36\" data-start=\"74.64\">Similarly</span></b><span style=\"color: #0070C0\"><sup><span data-end=\"76.00\" data-start=\"75.68\">7</span></sup></span>, <span data-end=\"76.32\" data-start=\"76.00\">products</span> <span data-end=\"76.52\" data-start=\"76.32\">that</span> <span data-end=\"76.64\" data-start=\"76.52\">are</span> <b id=\"wp_8\"><span data-end=\"76.86\" data-start=\"76.64\">aimed</span></b><span style=\"color: #0070C0\"><sup><span data-end=\"76.86\" data-start=\"76.86\">8</span></sup></span> <span data-end=\"77.06\" data-start=\"76.86\">at</span> <span data-end=\"77.46\" data-start=\"77.06\">children</span>, <span data-end=\"78.00\" data-start=\"77.82\">such</span> <span data-end=\"78.18\" data-start=\"78.00\">as</span> <span data-end=\"78.64\" data-start=\"78.18\">toys</span>, <span data-end=\"79.26\" data-start=\"78.94\">are</span> <span data-end=\"79.60\" data-start=\"79.26\">placed</span> <span data-end=\"79.82\" data-start=\"79.60\">on</span> <span data-end=\"80.16\" data-start=\"79.82\">lower</span> <span data-end=\"80.76\" data-start=\"80.16\">shelves</span> <span data-end=\"81.34\" data-start=\"80.76\">so</span> <span data-end=\"81.54\" data-start=\"81.34\">that</span> <span data-end=\"81.90\" data-start=\"81.54\">younger</span> <span data-end=\"82.44\" data-start=\"81.90\">shoppers</span> <span data-end=\"82.68\" data-start=\"82.44\">will</span> <span data-end=\"83.14\" data-start=\"82.68\">surely</span> <span data-end=\"83.52\" data-start=\"83.14\">see</span> <span data-end=\"83.86\" data-start=\"83.52\">them</span>. </div>"
            },
            "3": {
                "english_with_html": "<div class=\"paragraph\" data-paragraph=\"3\"><span data-end=\"86.02\" data-start=\"85.26\">Another</span> <b id=\"wr_4\"><span data-end=\"86.72\" data-start=\"86.38\">eye-catching</span></b>* <span data-end=\"87.40\" data-start=\"86.72\">convenience</span> <span data-end=\"87.76\" data-start=\"87.40\">store</span> <span data-end=\"88.32\" data-start=\"87.76\">strategy</span> <span data-end=\"88.90\" data-start=\"88.32\">is</span> <span data-end=\"89.10\" data-start=\"88.90\">to</span> <span data-end=\"89.40\" data-start=\"89.10\">promote</span> <b id=\"wp_9\"><span data-end=\"89.94\" data-start=\"89.40\">impulse</span></b><span style=\"color: #0070C0\"><sup><span data-end=\"89.94\" data-start=\"89.94\">9</span></sup>\n</span> <span data-end=\"90.48\" data-start=\"89.94\">purchases</span> <span data-end=\"90.88\" data-start=\"90.48\">of</span> <span data-end=\"91.28\" data-start=\"90.88\">small</span>, <span data-end=\"91.66\" data-start=\"91.64\">cheap</span> <span data-end=\"92.18\" data-start=\"91.66\">items</span> <span data-end=\"92.72\" data-start=\"92.18\">like</span> <span data-end=\"93.10\" data-start=\"92.72\">candy</span> <span data-end=\"93.46\" data-start=\"93.10\">bars</span>. <span data-end=\"94.62\" data-start=\"94.38\">These</span> <span data-end=\"94.78\" data-start=\"94.62\">are</span> <b id=\"wp_10\"><span data-end=\"95.26\" data-start=\"94.78\">displayed</span></b><span style=\"color: #0070C0\"><sup><span data-end=\"95.26\" data-start=\"95.26\">10</span></sup>\n</span> <span data-end=\"95.58\" data-start=\"95.26\">near</span> <b id=\"wr_5\"><span data-end=\"95.92\" data-start=\"95.58\">cash</span> <span data-end=\"96.40\" data-start=\"95.92\">registers</span></b>* <span data-end=\"97.12\" data-start=\"96.40\">and</span> <span data-end=\"97.28\" data-start=\"97.12\">are</span> <span data-end=\"97.62\" data-start=\"97.28\">thus</span> <span data-end=\"98.08\" data-start=\"97.62\">easily</span> <span data-end=\"98.58\" data-start=\"98.08\">noticed</span> <span data-end=\"99.14\" data-start=\"98.58\">and</span> <span style=\"color: #0070C0\">\n<b id=\"ip_2\"><span data-end=\"99.44\" data-start=\"99.14\">within</span></b>\n</span> <span data-end=\"99.80\" data-start=\"99.44\">quick</span> <span style=\"color: #0070C0\">\n<b id=\"ip_2\"><span data-end=\"100.22\" data-start=\"99.80\">reach</span></b></span>. <span data-end=\"101.40\" data-start=\"101.02\">Special</span> <b id=\"wp_11\"><span data-end=\"101.80\" data-start=\"101.40\">offers</span></b><span style=\"color: #0070C0\"><sup><span data-end=\"101.80\" data-start=\"101.80\">11</span></sup></span>, <span data-end=\"102.24\" data-start=\"101.80\">like</span> “<span data-end=\"102.60\" data-start=\"102.24\">buy</span> <span data-end=\"102.86\" data-start=\"102.60\">one</span>, <span data-end=\"103.08\" data-start=\"102.86\">get</span> <span data-end=\"103.30\" data-start=\"103.08\">one</span> <span data-end=\"103.64\" data-start=\"103.30\">free</span>,” <span data-end=\"104.42\" data-start=\"103.64\">make</span> <span data-end=\"104.72\" data-start=\"104.42\">such</span> <span data-end=\"105.10\" data-start=\"104.72\">little</span> “<span data-end=\"105.84\" data-start=\"105.10\">extras</span>” <span data-end=\"106.44\" data-start=\"105.84\">even</span> <span data-end=\"106.74\" data-start=\"106.44\">more</span> <span data-end=\"107.22\" data-start=\"106.74\">attractive</span>. <span data-end=\"108.26\" data-start=\"107.98\">Since</span> <b id=\"wp_12\"><span data-end=\"108.72\" data-start=\"108.26\">customers</span></b><span style=\"color: #0070C0\"><sup><span data-end=\"108.72\" data-start=\"108.72\">12</span></sup>\n</span> <span data-end=\"109.02\" data-start=\"108.72\">are</span> <span style=\"color: #0070C0\">\n<b id=\"ip_3\"><span data-end=\"109.34\" data-start=\"109.02\">lining</span> <span data-end=\"109.64\" data-start=\"109.34\">up</span></b>\n</span> <span data-end=\"109.82\" data-start=\"109.64\">at</span> <span data-end=\"110.14\" data-start=\"109.82\">cash</span> <span data-end=\"110.66\" data-start=\"110.14\">registers</span> <span data-end=\"111.24\" data-start=\"110.66\">to</span> <span data-end=\"111.48\" data-start=\"111.24\">pay</span> <span data-end=\"111.68\" data-start=\"111.48\">for</span> <span data-end=\"111.84\" data-start=\"111.68\">their</span> <span data-end=\"112.14\" data-start=\"111.84\">things</span> <span data-end=\"112.64\" data-start=\"112.14\">anyway</span>, <span data-end=\"113.42\" data-start=\"112.64\">these</span> <span data-end=\"113.84\" data-start=\"113.42\">items</span> <span data-end=\"114.12\" data-start=\"113.84\">can</span> <span data-end=\"114.62\" data-start=\"114.12\">easily</span> <span data-end=\"114.90\" data-start=\"114.62\">be</span> <span data-end=\"115.36\" data-start=\"114.90\">grabbed</span> <span data-end=\"115.90\" data-start=\"115.36\">and</span> <span data-end=\"116.26\" data-start=\"115.90\">added</span> <span data-end=\"116.54\" data-start=\"116.26\">to</span> <span data-end=\"116.76\" data-start=\"116.54\">their</span> <span data-end=\"117.22\" data-start=\"116.76\">shopping</span> <span data-end=\"117.82\" data-start=\"117.22\">baskets</span> <span data-end=\"118.32\" data-start=\"117.82\">on</span> <span data-end=\"118.76\" data-start=\"118.32\">impulse</span>. </div>"
            },
            "4": {
                "english_with_html": "<div class=\"paragraph\" data-paragraph=\"4\"><span data-end=\"120.48\" data-start=\"120.48\">A</span> <span data-end=\"120.78\" data-start=\"120.48\">third</span> <span data-end=\"121.32\" data-start=\"120.78\">strategy</span> <span data-end=\"121.60\" data-start=\"121.32\">is</span> <span data-end=\"121.78\" data-start=\"121.60\">to</span> <span data-end=\"121.92\" data-start=\"121.78\">make</span> <span data-end=\"122.50\" data-start=\"121.92\">customers</span> <span data-end=\"122.84\" data-start=\"122.50\">spend</span> <span data-end=\"123.12\" data-start=\"122.84\">more</span> <span data-end=\"123.58\" data-start=\"123.12\">time</span> <span data-end=\"123.86\" data-start=\"123.58\">in</span> <span data-end=\"124.36\" data-start=\"123.86\">stores</span> <span data-end=\"125.04\" data-start=\"124.36\">so</span> <span data-end=\"125.22\" data-start=\"125.04\">that</span> <span data-end=\"125.40\" data-start=\"125.22\">they</span> <span data-end=\"125.60\" data-start=\"125.40\">will</span> <span data-end=\"125.88\" data-start=\"125.60\">spend</span> <span data-end=\"126.10\" data-start=\"125.88\">more</span> <span data-end=\"126.46\" data-start=\"126.10\">money</span>, <span data-end=\"126.88\" data-start=\"126.46\">too</span>. <span data-end=\"127.98\" data-start=\"127.72\">Studies</span> <span data-end=\"128.28\" data-start=\"127.98\">have</span> <span data-end=\"128.58\" data-start=\"128.28\">shown</span> <span data-end=\"128.80\" data-start=\"128.58\">that</span> <span data-end=\"128.96\" data-start=\"128.80\">the</span> <span data-end=\"129.28\" data-start=\"128.96\">longer</span> <span data-end=\"129.74\" data-start=\"129.28\">people</span> <span data-end=\"130.12\" data-start=\"129.74\">stay</span> <span data-end=\"130.74\" data-start=\"130.12\">inside</span>, <span data-end=\"131.32\" data-start=\"131.18\">the</span> <span data-end=\"131.52\" data-start=\"131.32\">more</span> <span data-end=\"131.92\" data-start=\"131.52\">products</span> <span data-end=\"132.16\" data-start=\"131.92\">they</span> <span data-end=\"132.58\" data-start=\"132.16\">buy</span>. <span data-end=\"133.60\" data-start=\"133.34\">Shops</span> <span style=\"color: #0070C0\"><b id=\"ip_4\"><span data-end=\"133.86\" data-start=\"133.60\">take</span> </b><b id=\"wp_13\"><span data-end=\"134.30\" data-start=\"133.86\">advantage</span></b></span><span style=\"color: #0070C0\"><b><sup><span data-end=\"134.30\" data-start=\"134.30\">13</span></sup></b></span><span style=\"color: #0070C0\"><b id=\"ip_4\"> <span data-end=\"134.62\" data-start=\"134.30\">of</span></b></span> <span data-end=\"134.86\" data-start=\"134.62\">this</span> <span data-end=\"135.08\" data-start=\"134.86\">by</span> <span style=\"color: #0070C0\"><b id=\"ip_5\"><span data-end=\"135.44\" data-start=\"135.08\">setting</span> <span data-end=\"135.70\" data-start=\"135.44\">up</span></b></span> <span data-end=\"136.44\" data-start=\"136.04\">bar-style</span> <b id=\"wr_6\"><span data-end=\"136.90\" data-start=\"136.44\">seating</span></b>* <span data-end=\"137.52\" data-start=\"136.90\">or</span> <span data-end=\"137.90\" data-start=\"137.52\">dining</span> <span data-end=\"138.50\" data-start=\"137.90\">areas</span>. <span data-end=\"139.38\" data-start=\"139.08\">Here</span>, <span data-end=\"139.96\" data-start=\"139.38\">people</span> <span data-end=\"140.22\" data-start=\"139.96\">can</span> <span data-end=\"140.46\" data-start=\"140.22\">read</span> <span data-end=\"140.62\" data-start=\"140.46\">the</span> <span data-end=\"140.96\" data-start=\"140.62\">paper</span>, <span data-end=\"141.56\" data-start=\"141.34\">hold</span> <span data-end=\"141.72\" data-start=\"141.56\">a</span> <span data-end=\"142.04\" data-start=\"141.72\">meeting</span>, <span data-end=\"142.52\" data-start=\"142.36\">or</span> <span data-end=\"142.82\" data-start=\"142.52\">just</span> <span data-end=\"143.06\" data-start=\"142.82\">hang</span> <span data-end=\"143.50\" data-start=\"143.06\">out</span>. <span data-end=\"144.50\" data-start=\"144.00\">Although</span> <span data-end=\"144.84\" data-start=\"144.50\">these</span> <span data-end=\"145.32\" data-start=\"144.84\">customers</span> <span data-end=\"145.72\" data-start=\"145.32\">might</span> <span style=\"color: #0070C0\"><b id=\"ip_6\"><span data-end=\"146.16\" data-start=\"145.72\">start</span> <span data-end=\"146.46\" data-start=\"146.16\">off</span></b></span> <span data-end=\"146.66\" data-start=\"146.46\">with</span> <span data-end=\"146.92\" data-start=\"146.66\">just</span> <span data-end=\"147.08\" data-start=\"146.92\">a</span> <b id=\"wr_7\"><span data-end=\"147.42\" data-start=\"147.08\">beverage</span></b>*, <span data-end=\"148.30\" data-start=\"148.08\">they</span> <span data-end=\"148.64\" data-start=\"148.30\">often</span> <span data-end=\"148.94\" data-start=\"148.64\">grow</span> <span data-end=\"149.32\" data-start=\"148.94\">hungry</span> <span data-end=\"149.64\" data-start=\"149.32\">over</span> <span data-end=\"150.12\" data-start=\"149.64\">time</span>. <b id=\"wp_17\"><span data-end=\"151.48\" data-start=\"150.94\">Eventually</span></b><span style=\"color: #0070C0\"><sup><span data-end=\"151.96\" data-start=\"151.72\">14</span></sup></span>, <span data-end=\"152.32\" data-start=\"151.96\">they</span> <span data-end=\"152.54\" data-start=\"152.32\">end</span> <span data-end=\"152.74\" data-start=\"152.54\">up</span> <span data-end=\"153.18\" data-start=\"152.74\">purchas</span> <span data-end=\"153.18\" data-start=\"153.18\">ing</span> <span data-end=\"153.58\" data-start=\"153.18\">more</span> <span data-end=\"154.04\" data-start=\"153.58\">things</span> <span data-end=\"154.32\" data-start=\"154.04\">like</span> <span data-end=\"154.94\" data-start=\"154.32\">microwave</span> <span data-end=\"155.46\" data-start=\"154.94\">dinners</span> <span data-end=\"156.00\" data-start=\"155.46\">and</span> <span data-end=\"156.34\" data-start=\"156.00\">fruit</span> <span data-end=\"156.88\" data-start=\"156.34\">packs</span>. </div>"
            },
            "5": {
                "english_with_html": "<div class=\"paragraph\" data-paragraph=\"5\"><span data-end=\"158.78\" data-start=\"158.20\">To</span> <span data-end=\"159.16\" data-start=\"158.78\">avoid</span> <span data-end=\"159.58\" data-start=\"159.16\">falling</span> <span data-end=\"160.04\" data-start=\"159.58\">into</span> <span data-end=\"160.38\" data-start=\"160.04\">any</span> <span data-end=\"160.56\" data-start=\"160.38\">of</span> <span data-end=\"160.72\" data-start=\"160.56\">the</span> <b id=\"wp_15\"><span data-end=\"161.10\" data-start=\"160.72\">traps</span></b><span style=\"color: #0070C0\"><sup><span data-end=\"161.10\" data-start=\"161.10\">15</span></sup></span> <span data-end=\"161.56\" data-start=\"161.10\">above</span>, <span data-end=\"162.30\" data-start=\"162.04\">try</span> <span data-end=\"162.48\" data-start=\"162.30\">to</span> <span data-end=\"162.64\" data-start=\"162.48\">be</span> <span data-end=\"162.96\" data-start=\"162.64\">more</span> <b id=\"wp_16\"><span data-end=\"163.50\" data-start=\"162.96\">aware</span></b><span style=\"color: #0070C0\"><sup><span data-end=\"163.50\" data-start=\"163.50\">16</span></sup></span> <span data-end=\"163.82\" data-start=\"163.50\">of</span> <span data-end=\"164.00\" data-start=\"163.82\">the</span> <b id=\"wp_17\"><span data-end=\"164.28\" data-start=\"164.00\">clever</span></b><span style=\"color: #0070C0\"><sup><span data-end=\"164.28\" data-start=\"164.28\">17</span></sup></span> <span data-end=\"165.10\" data-start=\"164.28\">strategies</span> <span data-end=\"165.72\" data-start=\"165.10\">convenience</span> <span data-end=\"166.32\" data-start=\"165.72\">stores</span> <span data-end=\"166.84\" data-start=\"166.32\">use</span> <span data-end=\"167.38\" data-start=\"166.84\">to</span> <span data-end=\"167.60\" data-start=\"167.38\">get</span> <span data-end=\"168.04\" data-start=\"167.60\">deeper</span> <span data-end=\"168.38\" data-start=\"168.04\">into</span> <span data-end=\"168.62\" data-start=\"168.38\">your</span> <span data-end=\"168.98\" data-start=\"168.62\">pocket</span>. <span data-end=\"170.12\" data-start=\"169.52\">If</span> <span data-end=\"170.26\" data-start=\"170.12\">you</span> <span data-end=\"170.44\" data-start=\"170.26\">can</span> <span data-end=\"170.88\" data-start=\"170.44\">always</span> <span data-end=\"171.32\" data-start=\"170.88\">remember</span> <span data-end=\"171.60\" data-start=\"171.32\">the</span> <span data-end=\"171.96\" data-start=\"171.60\">tricks</span> <span data-end=\"172.22\" data-start=\"171.96\">that</span> <span data-end=\"172.54\" data-start=\"172.22\">shop</span> <span data-end=\"172.86\" data-start=\"172.54\">owners</span> <span data-end=\"173.32\" data-start=\"172.86\">use</span>, <span data-end=\"174.02\" data-start=\"173.62\">you</span> <span data-end=\"174.26\" data-start=\"174.02\">won’t</span> <span data-end=\"174.50\" data-start=\"174.26\">have</span> <span data-end=\"174.70\" data-start=\"174.50\">to</span> <span data-end=\"175.00\" data-start=\"174.70\">worry</span> <span data-end=\"175.42\" data-start=\"175.00\">about</span> <span data-end=\"175.90\" data-start=\"175.42\">spending</span> <span data-end=\"176.22\" data-start=\"175.90\">too</span> <span data-end=\"176.62\" data-start=\"176.22\">much</span>! </div>"
            }
        }
    }
}